resreg/__init__.py
resreg/resreg.py
resreg-0.2.dist-info/LICENSE
resreg-0.2.dist-info/METADATA
resreg-0.2.dist-info/WHEEL
resreg-0.2.dist-info/top_level.txt
resreg-0.2.dist-info/RECORD
