Metadata-Version: 2.1
Name: resreg
Version: 0.2
Summary: Resampling strategies for regression
Home-page: https://github.com/jafetgado/resreg
Author: Japheth Gado
Author-email: japhethgado@gmail.com
License: GNU GPLv3
Keywords: resampling regression machine-learning preprocessing
Platform: UNKNOWN
Classifier: Programming Language :: Python :: 3
Classifier: Operating System :: OS Independent
Classifier: Topic :: Scientific/Engineering
Requires-Python: >=3
Requires-Dist: numpy
Requires-Dist: pandas
Requires-Dist: scipy
Requires-Dist: scikit-learn
